tablepet/__init__.py
tablepet/pet.py
tablepet-1.0.dist-info/LICENSE
tablepet-1.0.dist-info/METADATA
tablepet-1.0.dist-info/WHEEL
tablepet-1.0.dist-info/top_level.txt
tablepet-1.0.dist-info/RECORD
